{
  "provider": "gnews",
  "fetchedAt": "2026-04-23T11:41:49.353Z",
  "sections": {
    "world": [
      {
        "title": "UK divers prepare for mine-clearing operations in Strait of Hormuz",
        "description": "Preparatory step comes on second day of London-hosted talks on reopening the strait.",
        "url": "https://www.politico.eu/article/uk-divers-mines-strait-of-hormuz/",
        "image": "https://www.politico.eu/cdn-cgi/image/width=1200,height=630,fit=crop,quality=80,onerror=redirect/wp-content/uploads/2026/04/23/GettyImages-2271914484-scaled.jpg",
        "publishedAt": "2026-04-22T23:39:57Z",
        "source": "politico.eu"
      },
      {
        "title": "Sanctions waiver on Russian oil purchase after request from over 10 countries: US",
        "description": "Bessent said the request to extend the sanctions waiver came on the sidelines of the Spring Meetings of the IMF and World Bank last week",
        "url": "https://www.moneycontrol.com/world/sanctions-waiver-on-russian-oil-purchase-after-request-from-over-10-countries-us-article-13896898.html",
        "image": "https://images.moneycontrol.com/static-mcnews/2026/04/20260418141930_Scott-Bessent-US.png",
        "publishedAt": "2026-04-22T23:39:43Z",
        "source": "Moneycontrol.com"
      },
      {
        "title": "Dad’s firm bankrupted by teen’s online spending spree",
        "description": "A TEENAGER in Henan, China, allegedly drove her father's company into bankruptcy after spending more than 17mil yuan (RM9.86mil) on livestream tips and online shopping, reported Sin Chew Daily.",
        "url": "https://www.thestar.com.my/news/nation/2026/04/23/dads-firm-bankrupted-by-teens-online-spending-spree",
        "image": "https://apicms.thestar.com.my/uploads/images/2026/04/23/3873529.jpeg",
        "publishedAt": "2026-04-22T23:39:43Z",
        "source": "The Star"
      },
      {
        "title": "No unilateral decisions on Straits of Malacca, says Mohamad",
        "description": "Foreign minister says decisions on the waterway must be made with the cooperation of Malaysia, Singapore, Indonesia, and Thailand.",
        "url": "https://www.freemalaysiatoday.com/category/nation/2026/04/23/no-unilateral-decisions-on-straits-of-malacca-says-mohamad",
        "image": "https://www.freemalaysiatoday.com/cdn-cgi/image/quality=75,format=auto,fit=cover,dpr=1,width=1200,height=630,gravity=center/https://media.freemalaysiatoday.com/wp-content/uploads/2026/04/10b776bf-13_mohamad_hasan_umno_deputy_president_moganraj_fmt_22042026-copy-copy.webp",
        "publishedAt": "2026-04-22T23:38:30Z",
        "source": "Free Malaysia Today"
      },
      {
        "title": "Police dragnet left this innocent man in prison for five years",
        "description": "At 17, Rasheed Wasiu was detained as security forces cracked down on protests against police brutality.",
        "url": "https://www.bbc.com/news/articles/cql7p9rd3gyo",
        "image": "https://ichef.bbci.co.uk/news/1024/branded_news/31ce/live/beef48b0-3ca1-11f1-8e26-931170ebc0de.jpg",
        "publishedAt": "2026-04-22T23:37:11Z",
        "source": "BBC"
      },
      {
        "title": "Edgar Lungu: Zambia's government takes possession of ex-president body in repatriation row",
        "description": "Zambia authorities and Edgar Lungu's family are in a dispute over where former leader's remains should be buried.",
        "url": "https://www.bbc.co.uk/news/articles/cdj7vgwwzgdo",
        "image": "https://ichef.bbci.co.uk/ace/branded_news/1200/cpsprodpb/5334/live/cd486880-77a1-11f0-ac7b-4783efd8e136.jpg",
        "publishedAt": "2026-04-22T23:33:37Z",
        "source": "BBC"
      },
      {
        "title": "Edgar Lungu: Zambia's government takes possession of ex",
        "description": "Zambia authorities and Edgar Lungu's family are in a dispute over where former leader's remains should be buried.",
        "url": "https://www.bbc.com/news/articles/cdj7vgwwzgdo",
        "image": "https://ichef.bbci.co.uk/news/1024/branded_news/5334/live/cd486880-77a1-11f0-ac7b-4783efd8e136.jpg",
        "publishedAt": "2026-04-22T23:33:37Z",
        "source": "BBC"
      },
      {
        "title": "German government prepares comprehensive control and travel restrictions for young people as part of reintroduction of conscription",
        "description": "The new Military Service Modernisation Act being introduced by the German government imposes far-reaching restrictions on travel freedoms for young people, demonstrating how extensive its plans are for the reintroduction of conscription and the militarisation of society.",
        "url": "https://www.wsws.org/en/articles/2026/04/22/vwfr-a22.html",
        "image": "https://www.wsws.org/asset/86e5fa90-b9ef-4786-80c1-9ab1f34b294b?rendition=1600x900",
        "publishedAt": "2026-04-22T23:31:27Z",
        "source": "World Socialist Web Site"
      }
    ],
    "business": [
      {
        "title": "Nigerian Couple Risks 50 Years for $500k Credit Card Fraud",
        "description": "A Nigerian man and his wife face up to 50 years in a US prison for an alleged $500,000 credit card fraud and identity theft scheme in New York.",
        "url": "https://punchng.com/500000-fraud-nigerian-wife-risk-50-years-in-us-prison/",
        "image": "https://cdn.punchng.com/wp-content/uploads/2025/06/05011816/n.jpeg",
        "publishedAt": "2026-04-22T23:37:30Z",
        "source": "Punch Newspapers"
      },
      {
        "title": "NGX Foreign Inflows Surge to N288bn in March 2026",
        "description": "Foreign portfolio inflows on the Nigerian Exchange (NGX) soared by 107.74% to N288.82bn in March, signaling renewed international investor confidence.",
        "url": "https://punchng.com/ngx-foreign-inflows-hit-n288bn-in-march/",
        "image": "https://cdn.punchng.com/wp-content/uploads/2021/05/02054604/NGX_Exchange_Identity.jpg",
        "publishedAt": "2026-04-22T23:37:30Z",
        "source": "Punch Newspapers"
      },
      {
        "title": "Malaysia vs China possible match up",
        "description": "It shapes up as a classic David vs Goliath clash, and Jun Hao will need to dig deep and draw on every ounce of resolve if he hopes to pull off an upset.",
        "url": "https://www.thestar.com.my/sport/badminton/2026/04/23/malaysia-vs-china-possible-match-up",
        "image": "https://apicms.thestar.com.my/uploads/images/2026/04/23/3873345.jpg",
        "publishedAt": "2026-04-22T23:34:32Z",
        "source": "The Star"
      },
      {
        "title": "Elon Musk says Optimus robot will be Tesla's 'biggest product ever'",
        "description": "Tesla CEO Elon Musk predicted its Optimus robot will soon be his company's most important product.",
        "url": "https://www.usatoday.com/story/cars/news/2026/04/22/elon-musk-tesla-optimus-robot-earnings-call/89741046007/",
        "image": "https://www.usatoday.com/gcdn/authoring/authoring-images/2026/02/13/NPPP/88664948007-20251106-t-124651-z-1509530971-rc-2-tqhalqmem-rtrmadp-3-chinatradeexpo.JPG?crop=6947,3909,x0,y513&width=3200&height=1801&format=pjpg&auto=webp",
        "publishedAt": "2026-04-22T23:33:00Z",
        "source": "USA Today"
      },
      {
        "title": "Forget the Lambo: Why Owning 100 Shares of OCBC Is the Ultimate Flex at 25",
        "description": "Owning 100 shares of OCBC may not look flashy, but it could be one of the smartest long-term wealth moves you can make.",
        "url": "https://thesmartinvestor.com.sg/forget-the-lambo-why-owning-100-shares-of-ocbc-is-the-ultimate-flex-at-25/",
        "image": "https://thesmartinvestor.com.sg/wp-content/uploads/2026/02/OCBC-Building.png",
        "publishedAt": "2026-04-22T23:30:00Z",
        "source": "The Smart Investor"
      },
      {
        "title": "Price Tracker: Oil, fuel monitor for Thursday, April 23",
        "description": "The oil shock is showing up beyond pump prices.",
        "url": "https://www.philstar.com/headlines/2026/04/23/2522829/price-tracker-oil-fuel-monitor-apr-23",
        "image": "https://media.philstar.com/photos/2026/04/03/price-tracker-11_2026-04-03_21-34-39.jpg",
        "publishedAt": "2026-04-22T23:30:00Z",
        "source": "Philstar.com"
      },
      {
        "title": "Hyundai Motor Connects with Next Generation of Football Fans through ‘Hyundai NEXT Cup Tour’ on ‘Top Eleven’",
        "description": "Hyundai Motor announced the launch of the ‘Hyundai NEXT Cup Tour,’ a new in-game event in ‘Top Eleven: Be a Football Manager’",
        "url": "https://www.hyundai.com/worldwide/en/newsroom/detail/0000001161",
        "image": "https://www.hyundai.com/content/dam/hyundai/ww/en/images/newsroom/news-image/2026/04/0423/highlight-horizontal-thumbnail-0423.jpg",
        "publishedAt": "2026-04-22T23:30:00Z",
        "source": "Hyundai"
      },
      {
        "title": "Guide for consumers to reduce energy use published",
        "description": "The Electricity Association of Ireland has published a guide for consumers to help them understand and reduce their household energy use amid what it said are \"ongoing concerns about energy affordability\".",
        "url": "https://www.rte.ie/news/ireland/2026/0423/1569667-eai-consumers-guide/",
        "image": "https://www.rte.ie/images/001b52d9-1600.jpg",
        "publishedAt": "2026-04-22T23:29:27Z",
        "source": "RTE.ie"
      }
    ],
    "science": [
      {
        "title": "Space Does Something Strange to Astronauts' Sense of Gravity",
        "description": "When astronauts come back down to Earth, it can take a moment to adjust to the return of gravity.",
        "url": "https://www.sciencealert.com/space-does-something-strange-to-astronauts-sense-of-gravity",
        "image": "https://www.sciencealert.com/images/2026/04/astronauts-iss.jpg",
        "publishedAt": "2026-04-22T23:34:40Z",
        "source": "ScienceAlert"
      },
      {
        "title": "Electronic origin of reorganization energy in interfacial electron transfer",
        "description": "Electron transfer (ET) reactions underpin energy conversion and chemical transformations in both biological1,2 and abiological3–5 systems. The efficiency of any ET process relies on achieving a desired ET rate within an optimal driving force range. Marcus theory6,7 provides a microscopic framework for understanding the activation free energy—and therefore the rate—of ET in terms of a key parameter: the reorganization energy. For electrified solid–liquid interfaces, it has long been conventionally understood that only factors in the electrolyte phase are responsible for determining the reorganization energy and that the electronic density of states (DOS) of the electrode only serves to dictate the number of thermally accessible channels for ET5,8–12. Here we show instead that the electrode DOS plays a central role in governing the reorganization energy, far outweighing its conventionally assumed role. Using atomically layered heterostructures, we tune the DOS of graphene and measure outer-sphere ET kinetics. We find the ensuing variation in ET rate arises from strong modulation in a reorganization energy associated with image potential localization in the electrode. Here we redefine the traditional paradigm of heterogeneous ET kinetics, revealing a deeper role of the electrode electronic structure in interfacial reactivity. By tuning graphene’s electronic density of states, the study shows electrode electronic structure—not just the electrolyte—dominates reorganization energy and thus controls outer-sphere electron-transfer rates at solid–liquid interfaces.",
        "url": "https://www.nature.com/articles/s41586-026-10311-2?error=cookies_not_supported&code=1166406d-408f-44d7-91ec-d64b55d7c181",
        "image": "https://media.springernature.com/m685/springer-static/image/art%3A10.1038%2Fs41586-026-10311-2/MediaObjects/41586_2026_10311_Fig1_HTML.png",
        "publishedAt": "2026-04-22T23:25:52Z",
        "source": "Nature"
      },
      {
        "title": "Efficiency-optimized relativistic plasma harmonics for extreme fields",
        "description": "Bright harmonic radiation from relativistically oscillating laser plasmas offers a direct route for generating extreme electromagnetic fields. Theory predicts that under optimized conditions, the plasma medium can support strong spatiotemporal compression of laser energy in a coherent harmonic focus (CHF), delivering intensity boosts many orders of magnitude greater than the incident driving laser pulse1–4. Although diffraction-limited performance5 (spatial compression) and attosecond phase locking6–8 (temporal compression) have been demonstrated experimentally, efficient coupling of relativistically intense laser pulse energy into the emitted harmonic cone has not been realized so far. Here we demonstrate that this highly nonlinear interaction can be tailored to deliver the maximum conversion efficiencies predicted from simulations. By fine-tuning the temporal profile of the driving laser on sub-picosecond (<10−12 s) timescales, energies >9 mJ between the 12th and 47th harmonics are observed. These results are in agreement with the theoretically expected efficiency dependence on harmonic order, verifying that optimal conditions have been achieved in the generation process. This is the important final element required to achieve the expected intensity boosts from a CHF in experiments. Although obtaining spatiotemporal compression and optimal efficiency simultaneously remains challenging, the path to realizing extreme optical field strengths approaching the critical field of quantum electrodynamics (the Schwinger limit at >1016 V cm−1 or >1029 W cm−2) is now open, permitting all-optical studies of the quantum vacuum and new frontiers for intense attosecond science. Tailoring relativistic laser–plasma interactions on femtosecond timescales unlocks a direct route to extreme field generation using a coherent harmonic focus.",
        "url": "https://www.nature.com/articles/s41586-026-10400-2?error=cookies_not_supported&code=92ace8ea-f3ff-43c1-861f-19865fee1ba9",
        "image": "https://media.springernature.com/m685/springer-static/image/art%3A10.1038%2Fs41586-026-10400-2/MediaObjects/41586_2026_10400_Fig1_HTML.png",
        "publishedAt": "2026-04-22T23:25:52Z",
        "source": "Nature"
      },
      {
        "title": "Exploding Stars, Black Holes, and the Forbidden Gap",
        "description": "An international team led by Monash University has uncovered evidence of a rare form of exploding star, helping to shed light on one of the most cataclysmic events in the universe. At the end of their lives, most massive stars collapse into black holes—objects with gravity so strong that not even light can escape. But some are completely destroyed in pair-instability supernova explosions. This can explain the so-named",
        "url": "https://www.universetoday.com/articles/exploding-stars-black-holes-and-the-forbidden-gap",
        "image": "https://www.universetoday.com/article_images/image_7519_1e-SN-2016iet_20260422_214813.jpg",
        "publishedAt": "2026-04-22T22:32:00Z",
        "source": "Universe Today"
      },
      {
        "title": "Strange creature with 24 eyes discovered in a Hong Kong pond",
        "description": "A previously unknown jellyfish, Tripedalia maipoensi, was discovered in Mai Po, a new find that expands Hong Kong's marine biodiversity.",
        "url": "https://www.earth.com/news/strange-new-jellyfish-tripedalia-maipoensi-has-24-eyes-discovered-in-hong-kong/",
        "image": "https://cff2.earth.com/uploads/2025/12/01154832/new-cubic-jellyfish-24-eyes-discovered-in-pond.jpg",
        "publishedAt": "2026-04-22T22:26:18Z",
        "source": "Earth.com"
      },
      {
        "title": "Quantum entanglement speed is measured for the first time",
        "description": "Quantum entanglement happens when two particles become interconnected and share a single state. Scientists have measured how fast it happens.",
        "url": "https://www.earth.com/news/quantum-entanglement-speed-measured-first-time-in-attoseconds-too-fast-to-comprehend/",
        "image": "https://cff2.earth.com/uploads/2026/03/22161205/quantum-entanglement_speed-measured_attoseconds_1m.jpg",
        "publishedAt": "2026-04-22T22:16:54Z",
        "source": "Earth.com"
      },
      {
        "title": "150-Year-Old Fossil Uncovers a Crucial Piece of Coelacanth Evolution, Bridging a 50-Million-Year Gap",
        "description": "A 150-year-old fossil at London’s Natural History Museum has revealed a new species of coelacanth, filling a critical gap in the fish's evolutionary timeline.",
        "url": "https://indiandefencereview.com/150-year-old-fossil-piece-of-coelacanth/",
        "image": "https://indiandefencereview.com/wp-content/uploads/2026/04/150-year-old-fossil-uncovers-a-crucial-piece-of-coelacanth-evolution-bridging-a-50-million-year-gap-scaled.png",
        "publishedAt": "2026-04-22T22:15:00Z",
        "source": "Indian Defence Review"
      },
      {
        "title": "New Technology Helps Flat-Faced Dogs Breathe Easy",
        "description": "Australian scientists have developed an injectable therapy that helps clear blocked airways in flat-faced dogs.  Biotechnology company Snoretox and RMIT University have shown early success using the first therapy from a",
        "url": "https://www.eurasiareview.com/23042026-new-technology-helps-flat-faced-dogs-breathe-easy/",
        "image": "https://www.eurasiareview.com/wp-content/uploads/2026/04/a-238.jpg",
        "publishedAt": "2026-04-22T22:07:01Z",
        "source": "Eurasia Review"
      }
    ],
    "ai": [
      {
        "title": "IBM shares fall 7%, drag Dow futures lower after results fail to ease AI concerns",
        "description": "According to analysts at Jefferies, investors were hoping for a better show from the IBM's Software business and that Wall Street would ask questions as to whether customers are delaying purchases with IBM while they test out other AI firms.",
        "url": "https://www.cnbctv18.com/market/ibm-q1-results-software-consulting-infra-business-2026-guidance-maintained-share-price-fall-19891584.htm",
        "image": "https://images.cnbctv18.com/uploads/2026/01/2026-01-28t211254z-1-lynxmpem0r1ej-rtroptp-4-davos-meeting-2026-01-dcfe15f89bf0c4216880b36c47070cf3-scaled.jpg?im=FitAndFill,width=500,height=300",
        "publishedAt": "2026-04-22T23:39:41Z",
        "source": "CNBC TV18"
      },
      {
        "title": "Ping Identity Wins 2026 Google Cloud Security Partner of the Year Award for Identity & Access Management",
        "description": "COMPANY NEWS:   Award highlights joint leadership in modernising and extending identity controls into real-time AI-driven environments Ping...",
        "url": "https://itwire.com/guest-articles/company-news/ping-identity-wins-2026-google-cloud-security-partner-of-the-year-award-for-identity-access-management.html",
        "image": "https://itwire.com/media/k2/items/cache/3a1f3c9dde56fdc195628d8ea879ea87_XS.jpg",
        "publishedAt": "2026-04-22T23:38:58Z",
        "source": "iTWire"
      },
      {
        "title": "Spotify Launches AI Credits for Music",
        "description": "Spotify has launched AI credits that will see the platform giving users the option of disclosing how the technology was used in creating their music.",
        "url": "https://www.billboard.com/pro/spotify-launches-ai-credits-music/",
        "image": "https://www.billboard.com/wp-content/uploads/2026/01/spotify-logo-brand-asset-2026-billboard-1800.jpg?w=1024",
        "publishedAt": "2026-04-22T23:38:18Z",
        "source": "Billboard"
      },
      {
        "title": "Tech Mahindra Presents Strategic AI Roadmap at Analyst Day 2026",
        "description": "Tech Mahindra held its Analyst Day 2026 on April 22, 2026, presenting strategic updates on AI-led transformation and delivery models. The comprehensive session covered technology evolution, financial performance, and the company's positioning across five waves of technological disruption from Y2K to AI revolution.",
        "url": "https://scanx.trade/stock-market-news/companies/tech-mahindra-concludes-q4-fy26-earnings-meeting-with-analysts-and-institutional-investors/38431337",
        "image": "http://news-images.dhan.co/tech-mahindra-concludes-q4-fy26-earnings-meeting-with-analysts-and-institutional-investors.jpg",
        "publishedAt": "2026-04-22T23:37:26Z",
        "source": "scanx.trade"
      },
      {
        "title": "Tesla's Ambitious AI and Robotics Investment Amidst Investor Skepticism",
        "description": "Tesla increases its annual spending to over $25 billion, focusing on AI and robotics for future revenue. While free cash flow is strong, investors remain cautious. Focus is on self-driving technology and robotics, including the launch of Cybercab and expansion plans for robotic cab services across multiple U.S. states.",
        "url": "https://www.devdiscourse.com/article/headlines/3883772-teslas-ambitious-ai-and-robotics-investment-amidst-investor-skepticism",
        "image": "https://www.devdiscourse.com/remote.axd?https://devdiscourse.blob.core.windows.net/aiimagegallery/17_09_2025_10_33_17_484576.png?width=920&format=jpeg",
        "publishedAt": "2026-04-22T23:30:37Z",
        "source": "Devdiscourse"
      },
      {
        "title": "Rubrik Secures and Accelerates AI Agents on Google Cloud",
        "description": "New Rubrik Agent Cloud Integration with Gemini Enterprise Agent Platform provides a unified control layer for AI agent operations Rubrik (NYSE: RBRK),...",
        "url": "https://itwire.com/business-it-news/data/rubrik-secures-and-accelerates-ai-agents-on-google-cloud.html",
        "image": "https://itwire.com/media/k2/items/cache/f65e61f645189a3ab26a115a5d6312f9_XS.jpg",
        "publishedAt": "2026-04-22T23:30:01Z",
        "source": "iTWire"
      },
      {
        "title": "A robot that uses AI is beating humans at table tennis",
        "description": "Advances in artificial intelligence are making robots more agile, as evidenced by one in Tokyo that plays table tennis.",
        "url": "https://www.bostonglobe.com/2026/04/22/business/robot-beats-human-table-tennis/",
        "image": "https://bostonglobe-prod.cdn.arcpublishing.com/resizer/v2/LYGAJ7QFNWJ7BNTFVQ5HBLTD6E.jpg?auth=f61d04c19dd45a9605de477db23015f4b8edd694d15ecfb5d60305676bbec50a&width=1440",
        "publishedAt": "2026-04-22T23:28:21Z",
        "source": "The Boston Globe"
      },
      {
        "title": "Google launches TPU 8 chips to speed AI training and cut costs",
        "description": "Google launched TPU 8t and TPU 8i AI chips built for model training, inference, and Gemini workloads.",
        "url": "https://interestingengineering.com/ai-robotics/google-tpu-8t-8i-ai-chips-launch",
        "image": "https://cms.interestingengineering.com/wp-content/uploads/2026/04/Google-TPU-8i.jpg",
        "publishedAt": "2026-04-22T23:26:58Z",
        "source": "Interesting Engineering"
      }
    ]
  }
}
